[
  {
    "category": "Lessons",
    "items": [
      { "title": "1. Introduction", "file": "lessons/01-intro.md", "type": "md" },
      { "title": "2. Getting Started", "file": "lessons/02-getting-started.md", "type": "md" },
      { "title": "3. Values and Datatypes", "file": "lessons/03-values-and-datatypes.md", "type": "md" }
    ]
  },
  {
    "category": "Exercises",
    "items": [
      { "title": "1. Hello, World!", "file": "exercises/01-hello-world.html", "type": "html" }
    ]
  },
  {
    "category": "DIY Questions",
    "items": [
      { "title": "1. Calculator", "file": "diy/01-calc.md", "type": "md" }
    ]
  }
]